{
  "Positions":[
    { "x": -3.779747, "y": 3.001444, "z": -1.781017 },
    { "x": 5.405638, "y": -4.875042, "z": -2.308036 },
    { "x": -6.256127, "y": 3.651773, "z": -1.043884 },
    { "x": -4.943297, "y": -2.213376, "z": 1.106262 },
    { "x": 3.115230, "y": 6.260139, "z": -2.047758 },
    { "x": -6.362499, "y": -4.401386, "z": 0.561079 },
    { "x": 0.965978, "y": 1.703606, "z": 5.013268 },
    { "x": 2.869593, "y": -1.590394, "z": -6.485163 },
    { "x": -0.055137, "y": 3.369676, "z": 6.824425 },
    { "x": 0.190300, "y": -4.471301, "z": 4.553949 },
    { "x": 1.340370, "y": 6.806784, "z": -2.226746 },
    { "x": -0.360375, "y": -3.350500, "z": 5.187423 },
    { "x": -1.608353, "y": 4.549558, "z": 2.696990 },
    { "x": 4.749136, "y": -2.260425, "z": -5.042171 },
    { "x": -3.844228, "y": 5.820265, "z": 3.393352 },
    { "x": -3.719502, "y": 0.609673, "z": -3.553267 },
    { "x": 4.938657, "y": -2.265090, "z": 4.412921 },
    { "x": -6.284919, "y": 0.768777, "z": -4.254748 }
  ],
  "Face": [
    { "x": 1, "y": 2, "z": 3 },
    { "x": 4, "y": 5, "z": 6 },
    { "x": 7, "y": 8, "z": 9 },
    { "x": 10, "y": 11, "z": 12 },
    { "x": 13, "y": 14, "z": 15 },
    { "x": 16, "y": 17, "z": 18 }
  ]
}